{
  "root": "higgsCombine_mStop1250_mLSP500_asimov_uncfix_bonly_uncfix.AsymptoticLimits.mH1250.root",
  "rows": [
    {
      "limit": 0.729949951171875,
      "limitErr": 0.0,
      "quantileExpected": 0.02500000037252903
    },
    {
      "limit": 0.9843599796295166,
      "limitErr": 0.0,
      "quantileExpected": 0.1599999964237213
    },
    {
      "limit": 1.39453125,
      "limitErr": 0.0,
      "quantileExpected": 0.5
    },
    {
      "limit": 2.000425338745117,
      "limitErr": 0.0,
      "quantileExpected": 0.8399999737739563
    },
    {
      "limit": 2.779224157333374,
      "limitErr": 0.0,
      "quantileExpected": 0.9750000238418579
    }
  ],
  "schema_version": "asymptotic_limit_summary_v1",
  "source": "corrected_uncertainty_recompute",
  "workspace": "workspace_mStop1250_mLSP500.root"
}
